odoo/addons/partner_email_check/README.rst
odoo/addons/partner_email_check/__init__.py
odoo/addons/partner_email_check/__manifest__.py
odoo/addons/partner_email_check/i18n/partner_email_check.pot
odoo/addons/partner_email_check/models/__init__.py
odoo/addons/partner_email_check/models/res_config_settings.py
odoo/addons/partner_email_check/models/res_partner.py
odoo/addons/partner_email_check/static/description/icon.png
odoo/addons/partner_email_check/tests/__init__.py
odoo/addons/partner_email_check/tests/test_partner_email_check.py
odoo/addons/partner_email_check/views/base_config_view.xml
odoo11_addon_partner_email_check-11.0.2.0.0.dist-info/METADATA
odoo11_addon_partner_email_check-11.0.2.0.0.dist-info/WHEEL
odoo11_addon_partner_email_check-11.0.2.0.0.dist-info/top_level.txt
odoo11_addon_partner_email_check-11.0.2.0.0.dist-info/RECORD
